{"proxies":{"com.tealium.titaniumandroid.ExampleProxy":{"superPackageName":"org.appcelerator.titanium.proxy","methods":{"printMessage":{"runOnUiThread":false,"hasInvocation":false,"args":[{"converter":"org.appcelerator.kroll.KrollConverter","defaultValueProvider":"org.appcelerator.kroll.KrollConverter","name":"message","sourceName":"message","type":"java.lang.String"}],"apiName":"printMessage","converter":"org.appcelerator.kroll.KrollConverter","defaultValueProvider":"org.appcelerator.kroll.KrollConverter","name":"__default_name__","returnType":"void"},"getMessage":{"runOnUiThread":false,"hasInvocation":false,"args":[],"apiName":"getMessage","converter":"org.appcelerator.kroll.KrollConverter","defaultValueProvider":"org.appcelerator.kroll.KrollConverter","name":"__default_name__","returnType":"java.lang.String"},"setMessage":{"runOnUiThread":false,"hasInvocation":false,"args":[{"converter":"org.appcelerator.kroll.KrollConverter","defaultValueProvider":"org.appcelerator.kroll.KrollConverter","name":"message","sourceName":"message","type":"java.lang.String"}],"apiName":"setMessage","converter":"org.appcelerator.kroll.KrollConverter","defaultValueProvider":"org.appcelerator.kroll.KrollConverter","name":"__default_name__","returnType":"void"}},"dynamicProperties":{"message":{"set":true,"nativeConverter":"org.appcelerator.kroll.KrollConverter","getMethodName":"getMessage","setMethodName":"setMessage","setMethodArgs":[{"converter":"org.appcelerator.kroll.KrollConverter","defaultValueProvider":"org.appcelerator.kroll.KrollConverter","name":"message","sourceName":"message","type":"java.lang.String"}],"setDefaultProviders":["org.appcelerator.kroll.KrollConverter"],"converter":"org.appcelerator.kroll.KrollConverter","defaultValueProvider":"org.appcelerator.kroll.KrollConverter","retain":true,"javascriptConverter":"org.appcelerator.kroll.KrollConverter","getHasInvocation":false,"runOnUiThread":false,"getMethodArgs":[],"getReturnType":"java.lang.String","setReturnType":"void","get":true,"name":"message","setHasInvocation":false,"getDefaultProviders":[]}},"superProxyBindingClassName":"org.appcelerator.titanium.proxy.TiViewProxyBindingGen","proxyClassName":"ExampleProxy","proxyAttrs":{"propertyAccessors":[],"fullAPIName":"TealiumTitaniumAndroid.Example","name":"Example","proxyClassName":"com.tealium.titaniumandroid.ExampleProxy","isTopLevel":false,"id":"com.tealium.titaniumandroid.ExampleProxy","creatableInModule":"com.tealium.titaniumandroid.TealiumTitaniumAndroidModule","parentModule":"org.appcelerator.kroll.annotations.Kroll.DEFAULT"},"packageName":"com.tealium.titaniumandroid","sourceName":"com.tealium.titaniumandroid.ExampleProxyBindingGen","superProxyClassName":"TiViewProxy","isModule":false,"genClassName":"ExampleProxyBindingGen"},"com.tealium.titaniumandroid.TealiumTitaniumAndroidModule":{"superPackageName":"org.appcelerator.kroll","methods":{"initTealium":{"runOnUiThread":false,"hasInvocation":false,"args":[{"converter":"org.appcelerator.kroll.KrollConverter","defaultValueProvider":"org.appcelerator.kroll.KrollConverter","name":"instanceName","sourceName":"instanceName","type":"java.lang.String"},{"converter":"org.appcelerator.kroll.KrollConverter","defaultValueProvider":"org.appcelerator.kroll.KrollConverter","name":"account","sourceName":"account","type":"java.lang.String"},{"converter":"org.appcelerator.kroll.KrollConverter","defaultValueProvider":"org.appcelerator.kroll.KrollConverter","name":"profile","sourceName":"profile","type":"java.lang.String"},{"converter":"org.appcelerator.kroll.KrollConverter","defaultValueProvider":"org.appcelerator.kroll.KrollConverter","name":"env","sourceName":"env","type":"java.lang.String"},{"converter":"org.appcelerator.kroll.KrollConverter","defaultValueProvider":"org.appcelerator.kroll.KrollConverter","name":"dataSourceId","sourceName":"dataSourceId","type":"java.lang.String"},{"converter":"org.appcelerator.kroll.KrollConverter","defaultValueProvider":"org.appcelerator.kroll.KrollConverter","name":"collectDispatchURL","sourceName":"collectDispatchURL","type":"java.lang.String"},{"converter":"org.appcelerator.kroll.KrollConverter","defaultValueProvider":"org.appcelerator.kroll.KrollConverter","name":"collectDispatchProfile","sourceName":"collectDispatchProfile","type":"java.lang.String"},{"converter":"org.appcelerator.kroll.KrollConverter","defaultValueProvider":"org.appcelerator.kroll.KrollConverter","name":"isLifecycleEnabled","sourceName":"isLifecycleEnabled","type":"boolean"}],"apiName":"initTealium","converter":"org.appcelerator.kroll.KrollConverter","defaultValueProvider":"org.appcelerator.kroll.KrollConverter","name":"__default_name__","returnType":"void"},"example":{"runOnUiThread":false,"hasInvocation":false,"args":[],"apiName":"example","converter":"org.appcelerator.kroll.KrollConverter","defaultValueProvider":"org.appcelerator.kroll.KrollConverter","name":"__default_name__","returnType":"java.lang.String"}},"dynamicProperties":{"exampleProp":{"set":true,"nativeConverter":"org.appcelerator.kroll.KrollConverter","getMethodName":"getExampleProp","setMethodName":"setExampleProp","setMethodArgs":[{"converter":"org.appcelerator.kroll.KrollConverter","defaultValueProvider":"org.appcelerator.kroll.KrollConverter","name":"value","sourceName":"value","type":"java.lang.String"}],"setDefaultProviders":["org.appcelerator.kroll.KrollConverter"],"converter":"org.appcelerator.kroll.KrollConverter","defaultValueProvider":"org.appcelerator.kroll.KrollConverter","retain":true,"javascriptConverter":"org.appcelerator.kroll.KrollConverter","getHasInvocation":false,"runOnUiThread":false,"getMethodArgs":[],"getReturnType":"java.lang.String","setReturnType":"void","get":true,"name":"exampleProp","setHasInvocation":false,"getDefaultProviders":[]}},"superProxyBindingClassName":"org.appcelerator.kroll.KrollModuleBindingGen","proxyClassName":"TealiumTitaniumAndroidModule","proxyAttrs":{"propertyAccessors":[],"fullAPIName":"TealiumTitaniumAndroid","name":"TealiumTitaniumAndroid","proxyClassName":"com.tealium.titaniumandroid.TealiumTitaniumAndroidModule","isTopLevel":false,"id":"com.tealium.titaniumandroid"},"packageName":"com.tealium.titaniumandroid","sourceName":"com.tealium.titaniumandroid.TealiumTitaniumAndroidModuleBindingGen","superProxyClassName":"KrollModule","isModule":true,"genClassName":"TealiumTitaniumAndroidModuleBindingGen","onAppCreate":"onAppCreate"}},"modules":{"com.tealium.titaniumandroid.TealiumTitaniumAndroidModule":{"apiName":"TealiumTitaniumAndroid","createProxies":[{"propertyAccessors":[],"fullAPIName":"TealiumTitaniumAndroid.Example","name":"Example","proxyClassName":"com.tealium.titaniumandroid.ExampleProxy","isTopLevel":false,"id":"com.tealium.titaniumandroid.ExampleProxy","creatableInModule":"com.tealium.titaniumandroid.TealiumTitaniumAndroidModule","parentModule":"org.appcelerator.kroll.annotations.Kroll.DEFAULT"}]}}}